ptresheaders/__init__.py
ptresheaders/_version.py
ptresheaders/ptresheaders.py
ptresheaders/modules/__init__.py
ptresheaders/modules/cors.py
ptresheaders/modules/leaks.py
ptresheaders/modules/headers/CC_cache_control.py
ptresheaders/modules/headers/CSPRO_content_security_policy_report_only.py
ptresheaders/modules/headers/CSP_content_security_policy.py
ptresheaders/modules/headers/CT_content_type.py
ptresheaders/modules/headers/FRAME_x_frame_options.py
ptresheaders/modules/headers/HSTS_strict_transport_security.py
ptresheaders/modules/headers/PERMPOL_permissions_policy.py
ptresheaders/modules/headers/REFPOL_referrer_policy.py
ptresheaders/modules/headers/RE_reporting_endpoints.py
ptresheaders/modules/headers/XCTO_x_content_type_options.py
ptresheaders/modules/headers/XDPC_x_dns_prefetch_control.py
ptresheaders/modules/headers/XTT_x_robots_tag.py
ptresheaders/modules/headers/__init__.py
ptresheaders/modules/headers/_header_test_base.py
ptresheaders-0.0.21.dist-info/licenses/LICENSE
ptresheaders-0.0.21.dist-info/METADATA
ptresheaders-0.0.21.dist-info/WHEEL
ptresheaders-0.0.21.dist-info/entry_points.txt
ptresheaders-0.0.21.dist-info/top_level.txt
ptresheaders-0.0.21.dist-info/RECORD
